{
"meta":{"test_sets":[],"test_metrics":[],"learn_metrics":[{"best_value":"Min","name":"MultiClass"}],"launch_mode":"Train","parameters":"","iteration_count":500,"learn_sets":["learn"],"name":"experiment"},
"iterations":[
{"learn":[0.6697268674],"iteration":0,"passed_time":0.06835028503,"remaining_time":34.10679223},
{"learn":[0.6464378509],"iteration":1,"passed_time":0.08671017387,"remaining_time":21.59083329},
{"learn":[0.6250266261],"iteration":2,"passed_time":0.1045969309,"remaining_time":17.32822489},
{"learn":[0.6087383655],"iteration":3,"passed_time":0.1272968876,"remaining_time":15.78481406},
{"learn":[0.5919716893],"iteration":4,"passed_time":0.1547131416,"remaining_time":15.31660102},
{"learn":[0.5745014713],"iteration":5,"passed_time":0.1809902424,"remaining_time":14.90152996},
{"learn":[0.5555609914],"iteration":6,"passed_time":0.2054574591,"remaining_time":14.47007533},
{"learn":[0.5381473281],"iteration":7,"passed_time":0.2352971084,"remaining_time":14.47077217},
{"learn":[0.5236752053],"iteration":8,"passed_time":0.2658735717,"remaining_time":14.50488041},
{"learn":[0.50925889],"iteration":9,"passed_time":0.2911860773,"remaining_time":14.26811779},
{"learn":[0.494119818],"iteration":10,"passed_time":0.3154651231,"remaining_time":14.02385865},
{"learn":[0.477930749],"iteration":11,"passed_time":0.3392411061,"remaining_time":13.79580498},
{"learn":[0.4638790857],"iteration":12,"passed_time":0.3647753535,"remaining_time":13.66504594},
{"learn":[0.450059378],"iteration":13,"passed_time":0.385969429,"remaining_time":13.39865303},
{"learn":[0.4355218081],"iteration":14,"passed_time":0.4054324512,"remaining_time":13.10898259},
{"learn":[0.4233872916],"iteration":15,"passed_time":0.4251204092,"remaining_time":12.85989238},
{"learn":[0.4112089071],"iteration":16,"passed_time":0.449412865,"remaining_time":12.76861258},
{"learn":[0.399553302],"iteration":17,"passed_time":0.4659918768,"remaining_time":12.47822692},
{"learn":[0.3881777538],"iteration":18,"passed_time":0.4846068368,"remaining_time":12.26820466},
{"learn":[0.3788077029],"iteration":19,"passed_time":0.504809437,"remaining_time":12.11542649},
{"learn":[0.3689750869],"iteration":20,"passed_time":0.5260506283,"remaining_time":11.99896433},
{"learn":[0.3588867347],"iteration":21,"passed_time":0.5506495253,"remaining_time":11.96411241},
{"learn":[0.3500520182],"iteration":22,"passed_time":0.571244278,"remaining_time":11.84710959},
{"learn":[0.3418171015],"iteration":23,"passed_time":0.5931568625,"remaining_time":11.76427777},
{"learn":[0.3344318327],"iteration":24,"passed_time":0.6139215078,"remaining_time":11.66450865},
{"learn":[0.3258286112],"iteration":25,"passed_time":0.6348160721,"remaining_time":11.57318531},
{"learn":[0.31779316],"iteration":26,"passed_time":0.6600901223,"remaining_time":11.56380103},
{"learn":[0.3094477257],"iteration":27,"passed_time":0.6815778538,"remaining_time":11.48945525},
{"learn":[0.3018935205],"iteration":28,"passed_time":0.7086276443,"remaining_time":11.50909036},
{"learn":[0.2942745372],"iteration":29,"passed_time":0.7289694676,"remaining_time":11.42052166},
{"learn":[0.2884350401],"iteration":30,"passed_time":0.7560087096,"remaining_time":11.43768015},
{"learn":[0.2811611906],"iteration":31,"passed_time":0.7772770333,"remaining_time":11.36767661},
{"learn":[0.2743297648],"iteration":32,"passed_time":0.798449961,"remaining_time":11.29927672},
{"learn":[0.2672496213],"iteration":33,"passed_time":0.818882826,"remaining_time":11.22351167},
{"learn":[0.2613013575],"iteration":34,"passed_time":0.8429428071,"remaining_time":11.19909729},
{"learn":[0.2549547445],"iteration":35,"passed_time":0.8635366452,"remaining_time":11.13002787},
{"learn":[0.2495034219],"iteration":36,"passed_time":0.8853435789,"remaining_time":11.07875884},
{"learn":[0.2447312833],"iteration":37,"passed_time":0.9058018592,"remaining_time":11.01264366},
{"learn":[0.2387772719],"iteration":38,"passed_time":0.9267237268,"remaining_time":10.95434969},
{"learn":[0.2342022284],"iteration":39,"passed_time":0.9633113649,"remaining_time":11.0780807},
{"learn":[0.2285695784],"iteration":40,"passed_time":0.9863111318,"remaining_time":11.0418734},
{"learn":[0.2229883865],"iteration":41,"passed_time":1.009577428,"remaining_time":11.00920147},
{"learn":[0.2190022159],"iteration":42,"passed_time":1.034078572,"remaining_time":10.99009087},
{"learn":[0.2144122116],"iteration":43,"passed_time":1.057934415,"remaining_time":10.96404758},
{"learn":[0.2090188967],"iteration":44,"passed_time":1.082767102,"remaining_time":10.94797848},
{"learn":[0.2052658285],"iteration":45,"passed_time":1.103788379,"remaining_time":10.8939114},
{"learn":[0.2006261111],"iteration":46,"passed_time":1.125385083,"remaining_time":10.84679665},
{"learn":[0.1953492833],"iteration":47,"passed_time":1.150203697,"remaining_time":10.83108481},
{"learn":[0.1904762752],"iteration":48,"passed_time":1.171578737,"remaining_time":10.78330634},
{"learn":[0.1863674608],"iteration":49,"passed_time":1.194408754,"remaining_time":10.74967879},
{"learn":[0.1828646656],"iteration":50,"passed_time":1.216281118,"remaining_time":10.70804357},
{"learn":[0.1792006084],"iteration":51,"passed_time":1.241005333,"remaining_time":10.69173825},
{"learn":[0.1747101584],"iteration":52,"passed_time":1.262008044,"remaining_time":10.64372822},
{"learn":[0.1708538313],"iteration":53,"passed_time":1.292943791,"remaining_time":10.67875798},
{"learn":[0.1670953432],"iteration":54,"passed_time":1.311034357,"remaining_time":10.6074598},
{"learn":[0.1632957347],"iteration":55,"passed_time":1.330225401,"remaining_time":10.54678711},
{"learn":[0.1593456939],"iteration":56,"passed_time":1.363157713,"remaining_time":10.59436609},
{"learn":[0.1569274789],"iteration":57,"passed_time":1.379507069,"remaining_time":10.51279525},
{"learn":[0.1537285558],"iteration":58,"passed_time":1.395634444,"remaining_time":10.4317761},
{"learn":[0.1507752982],"iteration":59,"passed_time":1.412101542,"remaining_time":10.3554113},
{"learn":[0.147511157],"iteration":60,"passed_time":1.428747621,"remaining_time":10.28229845},
{"learn":[0.1440307049],"iteration":61,"passed_time":1.445631981,"remaining_time":10.21269045},
{"learn":[0.1412625481],"iteration":62,"passed_time":1.465064464,"remaining_time":10.16243128},
{"learn":[0.1386989918],"iteration":63,"passed_time":1.481776955,"remaining_time":10.09460551},
{"learn":[0.1366218261],"iteration":64,"passed_time":1.501171958,"remaining_time":10.04630464},
{"learn":[0.1342627953],"iteration":65,"passed_time":1.519312321,"remaining_time":9.990629502},
{"learn":[0.1316147267],"iteration":66,"passed_time":1.53705806,"remaining_time":9.933524477},
{"learn":[0.129596814],"iteration":67,"passed_time":1.559474837,"remaining_time":9.907251905},
{"learn":[0.12680202],"iteration":68,"passed_time":1.577277104,"remaining_time":9.85226713},
{"learn":[0.1242588971],"iteration":69,"passed_time":1.597862752,"remaining_time":9.815442619},
{"learn":[0.1215280019],"iteration":70,"passed_time":1.618330654,"remaining_time":9.778364093},
{"learn":[0.1197171138],"iteration":71,"passed_time":1.637806319,"remaining_time":9.735848671},
{"learn":[0.1181417398],"iteration":72,"passed_time":1.663002782,"remaining_time":9.727427234},
{"learn":[0.1161486738],"iteration":73,"passed_time":1.687032433,"remaining_time":9.711835358},
{"learn":[0.1146843431],"iteration":74,"passed_time":1.715502777,"remaining_time":9.721182401},
{"learn":[0.1125298704],"iteration":75,"passed_time":1.7318413,"remaining_time":9.661851461},
{"learn":[0.110543602],"iteration":76,"passed_time":1.751884107,"remaining_time":9.623986718},
{"learn":[0.1091424355],"iteration":77,"passed_time":1.773493609,"remaining_time":9.595055164},
{"learn":[0.1075352685],"iteration":78,"passed_time":1.793889725,"remaining_time":9.55984271},
{"learn":[0.1056892026],"iteration":79,"passed_time":1.81464624,"remaining_time":9.526892758},
{"learn":[0.1038401966],"iteration":80,"passed_time":1.835408475,"remaining_time":9.494273468},
{"learn":[0.1021738731],"iteration":81,"passed_time":1.859480981,"remaining_time":9.478817682},
{"learn":[0.1008214124],"iteration":82,"passed_time":1.879648728,"remaining_time":9.44353638},
{"learn":[0.09936634406],"iteration":83,"passed_time":1.900246609,"remaining_time":9.410745112},
{"learn":[0.09750614043],"iteration":84,"passed_time":1.922133231,"remaining_time":9.384532834},
{"learn":[0.09615671916],"iteration":85,"passed_time":1.942441915,"remaining_time":9.35082503},
{"learn":[0.09443513554],"iteration":86,"passed_time":1.965648217,"remaining_time":9.331180618},
{"learn":[0.09309127391],"iteration":87,"passed_time":1.987466669,"remaining_time":9.304957587},
{"learn":[0.09134843877],"iteration":88,"passed_time":2.008079267,"remaining_time":9.273264932},
{"learn":[0.08968249155],"iteration":89,"passed_time":2.028667062,"remaining_time":9.241705505},
{"learn":[0.08839516543],"iteration":90,"passed_time":2.05322148,"remaining_time":9.228215225},
{"learn":[0.08676372848],"iteration":91,"passed_time":2.074140476,"remaining_time":9.198362111},
{"learn":[0.08524949642],"iteration":92,"passed_time":2.0945386,"remaining_time":9.166421616},
{"learn":[0.08385782207],"iteration":93,"passed_time":2.114941184,"remaining_time":9.134745966},
{"learn":[0.08288590531],"iteration":94,"passed_time":2.136337174,"remaining_time":9.107542691},
{"learn":[0.08141191411],"iteration":95,"passed_time":2.160226979,"remaining_time":9.090955202},
{"learn":[0.0799797688],"iteration":96,"passed_time":2.181783261,"remaining_time":9.064522208},
{"learn":[0.07863031689],"iteration":97,"passed_time":2.202870879,"remaining_time":9.036266259},
{"learn":[0.07749583238],"iteration":98,"passed_time":2.223223358,"remaining_time":9.005177439},
{"learn":[0.07611477292],"iteration":99,"passed_time":2.258245204,"remaining_time":9.032980818},
{"learn":[0.07492686958],"iteration":100,"passed_time":2.278891831,"remaining_time":9.002750895},
{"learn":[0.07391372953],"iteration":101,"passed_time":2.313052375,"remaining_time":9.025439658},
{"learn":[0.0731091633],"iteration":102,"passed_time":2.332569919,"remaining_time":8.990585029},
{"learn":[0.07198533291],"iteration":103,"passed_time":2.356767107,"remaining_time":8.973843986},
{"learn":[0.07107821079],"iteration":104,"passed_time":2.372522544,"remaining_time":8.925203857},
{"learn":[0.06991840005],"iteration":105,"passed_time":2.393097435,"remaining_time":8.895098013},
{"learn":[0.06883200443],"iteration":106,"passed_time":2.414824765,"remaining_time":8.869403108},
{"learn":[0.06782888222],"iteration":107,"passed_time":2.43606106,"remaining_time":8.841999402},
{"learn":[0.06679768999],"iteration":108,"passed_time":2.461488845,"remaining_time":8.829744388},
{"learn":[0.06575263145],"iteration":109,"passed_time":2.482298324,"remaining_time":8.800875875},
{"learn":[0.06496146582],"iteration":110,"passed_time":2.501326074,"remaining_time":8.765908494},
{"learn":[0.06420823251],"iteration":111,"passed_time":2.521743925,"remaining_time":8.736041456},
{"learn":[0.06315725415],"iteration":112,"passed_time":2.546425529,"remaining_time":8.72094407},
{"learn":[0.06218312999],"iteration":113,"passed_time":2.565650301,"remaining_time":8.687201895},
{"learn":[0.0612088275],"iteration":114,"passed_time":2.588570442,"remaining_time":8.666083655},
{"learn":[0.06035539064],"iteration":115,"passed_time":2.610455717,"remaining_time":8.64150858},
{"learn":[0.0598090598],"iteration":116,"passed_time":2.635480165,"remaining_time":8.627255583},
{"learn":[0.05908304724],"iteration":117,"passed_time":2.660003131,"remaining_time":8.611196578},
{"learn":[0.05827876902],"iteration":118,"passed_time":2.685628601,"remaining_time":8.598525184},
{"learn":[0.0575824979],"iteration":119,"passed_time":2.716377349,"remaining_time":8.601861606},
{"learn":[0.05669016417],"iteration":120,"passed_time":2.738428994,"remaining_time":8.577393295},
{"learn":[0.05602662731],"iteration":121,"passed_time":2.766643503,"remaining_time":8.572059377},
{"learn":[0.05537356487],"iteration":122,"passed_time":2.795881507,"remaining_time":8.569490473},
{"learn":[0.05481636751],"iteration":123,"passed_time":2.817638763,"remaining_time":8.543807861},
{"learn":[0.05408562831],"iteration":124,"passed_time":2.845363409,"remaining_time":8.536090226},
{"learn":[0.05334348783],"iteration":125,"passed_time":2.864785639,"remaining_time":8.50341134},
{"learn":[0.05275439839],"iteration":126,"passed_time":2.891723082,"remaining_time":8.493013462},
{"learn":[0.05211664649],"iteration":127,"passed_time":2.91646514,"remaining_time":8.475976813},
{"learn":[0.05150041314],"iteration":128,"passed_time":2.944876478,"remaining_time":8.469373438},
{"learn":[0.05087222515],"iteration":129,"passed_time":2.968533896,"remaining_time":8.448904165},
{"learn":[0.05019636325],"iteration":130,"passed_time":2.99103687,"remaining_time":8.425134391},
{"learn":[0.04959331356],"iteration":131,"passed_time":3.011797304,"remaining_time":8.396525818},
{"learn":[0.04908559113],"iteration":132,"passed_time":3.034513231,"remaining_time":8.373431245},
{"learn":[0.04848104828],"iteration":133,"passed_time":3.054364506,"remaining_time":8.34251798},
{"learn":[0.04797341783],"iteration":134,"passed_time":3.074221903,"remaining_time":8.311785145},
{"learn":[0.04726598782],"iteration":135,"passed_time":3.094008747,"remaining_time":8.281023412},
{"learn":[0.04662728526],"iteration":136,"passed_time":3.113307012,"remaining_time":8.249127339},
{"learn":[0.04614337338],"iteration":137,"passed_time":3.134221569,"remaining_time":8.221653682},
{"learn":[0.04556028787],"iteration":138,"passed_time":3.155911909,"remaining_time":8.196289201},
{"learn":[0.04511195175],"iteration":139,"passed_time":3.178329075,"remaining_time":8.172846194},
{"learn":[0.0445636506],"iteration":140,"passed_time":3.201201514,"remaining_time":8.150576904},
{"learn":[0.04407836319],"iteration":141,"passed_time":3.224656695,"remaining_time":8.129768287},
{"learn":[0.04380225676],"iteration":142,"passed_time":3.246561262,"remaining_time":8.105051543},
{"learn":[0.04341091912],"iteration":143,"passed_time":3.266979254,"remaining_time":8.076698712},
{"learn":[0.04289889723],"iteration":144,"passed_time":3.287490225,"remaining_time":8.048682964},
{"learn":[0.04258010537],"iteration":145,"passed_time":3.308121712,"remaining_time":8.021062233},
{"learn":[0.04208305008],"iteration":146,"passed_time":3.329601135,"remaining_time":7.995572795},
{"learn":[0.04168775636],"iteration":147,"passed_time":3.350341224,"remaining_time":7.968379127},
{"learn":[0.04127498515],"iteration":148,"passed_time":3.370897743,"remaining_time":7.94083965},
{"learn":[0.04080433497],"iteration":149,"passed_time":3.390981894,"remaining_time":7.912291086},
{"learn":[0.04050418161],"iteration":150,"passed_time":3.410470222,"remaining_time":7.882477533},
{"learn":[0.04010417716],"iteration":151,"passed_time":3.434038778,"remaining_time":7.862141414},
{"learn":[0.03961696739],"iteration":152,"passed_time":3.453561286,"remaining_time":7.832586708},
{"learn":[0.0391423124],"iteration":153,"passed_time":3.47330736,"remaining_time":7.803664588},
{"learn":[0.03865635334],"iteration":154,"passed_time":3.493235253,"remaining_time":7.775265562},
{"learn":[0.03820792278],"iteration":155,"passed_time":3.513117944,"remaining_time":7.746875467},
{"learn":[0.0379255429],"iteration":156,"passed_time":3.533791645,"remaining_time":7.720321875},
{"learn":[0.03752156522],"iteration":157,"passed_time":3.555204818,"remaining_time":7.695443339},
{"learn":[0.03707124119],"iteration":158,"passed_time":3.578118864,"remaining_time":7.673827249},
{"learn":[0.03676349751],"iteration":159,"passed_time":3.602857276,"remaining_time":7.656071712},
{"learn":[0.03643592276],"iteration":160,"passed_time":3.622446074,"remaining_time":7.627386454},
{"learn":[0.03603707866],"iteration":161,"passed_time":3.644393262,"remaining_time":7.603734089},
{"learn":[0.03562593027],"iteration":162,"passed_time":3.667752853,"remaining_time":7.58302277},
{"learn":[0.03523522334],"iteration":163,"passed_time":3.689657761,"remaining_time":7.559298828},
{"learn":[0.03486497855],"iteration":164,"passed_time":3.710814695,"remaining_time":7.534078321},
{"learn":[0.0345018937],"iteration":165,"passed_time":3.732988146,"remaining_time":7.510952053},
{"learn":[0.03415456624],"iteration":166,"passed_time":3.755133371,"remaining_time":7.487780913},
{"learn":[0.03376876951],"iteration":167,"passed_time":3.783710344,"remaining_time":7.477332346},
{"learn":[0.03346241182],"iteration":168,"passed_time":3.812999836,"remaining_time":7.468064767},
{"learn":[0.03316343467],"iteration":169,"passed_time":3.837840673,"remaining_time":7.449926012},
{"learn":[0.03279125783],"iteration":170,"passed_time":3.859717076,"remaining_time":7.426005368},
{"learn":[0.03252672164],"iteration":171,"passed_time":3.882177249,"remaining_time":7.40322173},
{"learn":[0.03218677245],"iteration":172,"passed_time":3.911450879,"remaining_time":7.393320448},
{"learn":[0.03190781044],"iteration":173,"passed_time":3.943111041,"remaining_time":7.387667813},
{"learn":[0.03161481068],"iteration":174,"passed_time":3.971629095,"remaining_time":7.375882605},
{"learn":[0.03130994294],"iteration":175,"passed_time":4.001058385,"remaining_time":7.365584755},
{"learn":[0.03104038613],"iteration":176,"passed_time":4.02147556,"remaining_time":7.338624892},
{"learn":[0.03079305563],"iteration":177,"passed_time":4.043315382,"remaining_time":7.314312096},
{"learn":[0.03053432133],"iteration":178,"passed_time":4.05992335,"remaining_time":7.280644667},
{"learn":[0.03032429111],"iteration":179,"passed_time":4.076764425,"remaining_time":7.2475812},
{"learn":[0.03003171855],"iteration":180,"passed_time":4.092605398,"remaining_time":7.212934376},
{"learn":[0.02976359813],"iteration":181,"passed_time":4.10723205,"remaining_time":7.176372483},
{"learn":[0.02955292276],"iteration":182,"passed_time":4.12764714,"remaining_time":7.150077287},
{"learn":[0.02931085553],"iteration":183,"passed_time":4.145571756,"remaining_time":7.119568885},
{"learn":[0.02903630849],"iteration":184,"passed_time":4.159794088,"remaining_time":7.082892637},
{"learn":[0.0288512449],"iteration":185,"passed_time":4.17390166,"remaining_time":7.046264092},
{"learn":[0.02859609959],"iteration":186,"passed_time":4.188443054,"remaining_time":7.010602545},
{"learn":[0.02839301378],"iteration":187,"passed_time":4.203878346,"remaining_time":6.97664917},
{"learn":[0.02814336116],"iteration":188,"passed_time":4.224429499,"remaining_time":6.951309916},
{"learn":[0.02794073071],"iteration":189,"passed_time":4.240100327,"remaining_time":6.918058429},
{"learn":[0.02771057041],"iteration":190,"passed_time":4.256754369,"remaining_time":6.886581675},
{"learn":[0.02747865016],"iteration":191,"passed_time":4.276204737,"remaining_time":6.859745098},
{"learn":[0.0272568428],"iteration":192,"passed_time":4.295992465,"remaining_time":6.833521693},
{"learn":[0.02706261701],"iteration":193,"passed_time":4.321152308,"remaining_time":6.815838176},
{"learn":[0.02682766229],"iteration":194,"passed_time":4.340271022,"remaining_time":6.788629035},
{"learn":[0.02659842206],"iteration":195,"passed_time":4.36259351,"remaining_time":6.766471567},
{"learn":[0.02648816477],"iteration":196,"passed_time":4.383311121,"remaining_time":6.741844009},
{"learn":[0.02625293938],"iteration":197,"passed_time":4.401094986,"remaining_time":6.712781242},
{"learn":[0.02603180751],"iteration":198,"passed_time":4.423414258,"remaining_time":6.690691917},
{"learn":[0.02589148713],"iteration":199,"passed_time":4.446821129,"remaining_time":6.670231694},
{"learn":[0.02569970257],"iteration":200,"passed_time":4.468949559,"remaining_time":6.647840389},
{"learn":[0.02552797709],"iteration":201,"passed_time":4.491923736,"remaining_time":6.626699372},
{"learn":[0.02536326087],"iteration":202,"passed_time":4.515584518,"remaining_time":6.606544837},
{"learn":[0.02522991624],"iteration":203,"passed_time":4.538454504,"remaining_time":6.585208495},
{"learn":[0.02508713503],"iteration":204,"passed_time":4.561581199,"remaining_time":6.564226603},
{"learn":[0.02489798538],"iteration":205,"passed_time":4.583339911,"remaining_time":6.541271523},
{"learn":[0.02469396075],"iteration":206,"passed_time":4.604762537,"remaining_time":6.517852286},
{"learn":[0.02457415236],"iteration":207,"passed_time":4.631322849,"remaining_time":6.501664769},
{"learn":[0.02443730205],"iteration":208,"passed_time":4.648175711,"remaining_time":6.471861875},
{"learn":[0.02428288093],"iteration":209,"passed_time":4.670611135,"remaining_time":6.449891567},
{"learn":[0.02417202527],"iteration":210,"passed_time":4.688082326,"remaining_time":6.421117498},
{"learn":[0.0240567625],"iteration":211,"passed_time":4.705156071,"remaining_time":6.391910134},
{"learn":[0.02385931224],"iteration":212,"passed_time":4.728606376,"remaining_time":6.371408591},
{"learn":[0.02368424685],"iteration":213,"passed_time":4.745962643,"remaining_time":6.342735121},
{"learn":[0.02353211513],"iteration":214,"passed_time":4.763722794,"remaining_time":6.314702308},
{"learn":[0.02336878509],"iteration":215,"passed_time":4.780818245,"remaining_time":6.285890655},
{"learn":[0.023217469],"iteration":216,"passed_time":4.798330981,"remaining_time":6.257731187},
{"learn":[0.02301774846],"iteration":217,"passed_time":4.820662976,"remaining_time":6.235903482},
{"learn":[0.0228483366],"iteration":218,"passed_time":4.838026881,"remaining_time":6.207696592},
{"learn":[0.02268523832],"iteration":219,"passed_time":4.861376453,"remaining_time":6.187206395},
{"learn":[0.0226009488],"iteration":220,"passed_time":4.880161449,"remaining_time":6.160927802},
{"learn":[0.02250345613],"iteration":221,"passed_time":4.898808986,"remaining_time":6.134544586},
{"learn":[0.02234351076],"iteration":222,"passed_time":4.915415803,"remaining_time":6.105695864},
{"learn":[0.02218316272],"iteration":223,"passed_time":4.933338241,"remaining_time":6.078577476},
{"learn":[0.02201530603],"iteration":224,"passed_time":4.953356827,"remaining_time":6.054102789},
{"learn":[0.02186521349],"iteration":225,"passed_time":4.969198375,"remaining_time":6.024603339},
{"learn":[0.0217362829],"iteration":226,"passed_time":4.984201681,"remaining_time":5.994216118},
{"learn":[0.02157676307],"iteration":227,"passed_time":5.004415663,"remaining_time":5.970180089},
{"learn":[0.02142612149],"iteration":228,"passed_time":5.018871662,"remaining_time":5.939363408},
{"learn":[0.0213261242],"iteration":229,"passed_time":5.03931657,"remaining_time":5.915719452},
{"learn":[0.02120476015],"iteration":230,"passed_time":5.060981738,"remaining_time":5.893524189},
{"learn":[0.02105774065],"iteration":231,"passed_time":5.08270737,"remaining_time":5.871403341},
{"learn":[0.02093599025],"iteration":232,"passed_time":5.106310405,"remaining_time":5.851437245},
{"learn":[0.02079552876],"iteration":233,"passed_time":5.129201725,"remaining_time":5.830631021},
{"learn":[0.02066078274],"iteration":234,"passed_time":5.151314802,"remaining_time":5.808929458},
{"learn":[0.02050751149],"iteration":235,"passed_time":5.173441152,"remaining_time":5.787239255},
{"learn":[0.02034845054],"iteration":236,"passed_time":5.193720863,"remaining_time":5.763496148},
{"learn":[0.02023207873],"iteration":237,"passed_time":5.215134684,"remaining_time":5.741030619},
{"learn":[0.02008821477],"iteration":238,"passed_time":5.232806352,"remaining_time":5.714487271},
{"learn":[0.01994591951],"iteration":239,"passed_time":5.249148852,"remaining_time":5.686577923},
{"learn":[0.01979335891],"iteration":240,"passed_time":5.264013662,"remaining_time":5.657176508},
{"learn":[0.0196621657],"iteration":241,"passed_time":5.280709637,"remaining_time":5.629847464},
{"learn":[0.01955971192],"iteration":242,"passed_time":5.298050209,"remaining_time":5.603287669},
{"learn":[0.01943562622],"iteration":243,"passed_time":5.31389692,"remaining_time":5.575236113},
{"learn":[0.01931665445],"iteration":244,"passed_time":5.330740044,"remaining_time":5.54832127},
{"learn":[0.01920450339],"iteration":245,"passed_time":5.346199037,"remaining_time":5.520059168},
{"learn":[0.01913806686],"iteration":246,"passed_time":5.362023168,"remaining_time":5.492274743},
{"learn":[0.01902420853],"iteration":247,"passed_time":5.377983173,"remaining_time":5.464724837},
{"learn":[0.01890708947],"iteration":248,"passed_time":5.397032922,"remaining_time":5.440382584},
{"learn":[0.0187970208],"iteration":249,"passed_time":5.412767881,"remaining_time":5.412767881},
{"learn":[0.01870073721],"iteration":250,"passed_time":5.429105612,"remaining_time":5.385845807},
{"learn":[0.0185906034],"iteration":251,"passed_time":5.444639115,"remaining_time":5.358216272},
{"learn":[0.01846671252],"iteration":252,"passed_time":5.463994218,"remaining_time":5.334413327},
{"learn":[0.01841137458],"iteration":253,"passed_time":5.487492413,"remaining_time":5.314658006},
{"learn":[0.01828255602],"iteration":254,"passed_time":5.50873728,"remaining_time":5.292708367},
{"learn":[0.01816383853],"iteration":255,"passed_time":5.530024814,"remaining_time":5.270804901},
{"learn":[0.01806401682],"iteration":256,"passed_time":5.55103792,"remaining_time":5.248646749},
{"learn":[0.01796833313],"iteration":257,"passed_time":5.572417713,"remaining_time":5.226841421},
{"learn":[0.01786643776],"iteration":258,"passed_time":5.597449216,"remaining_time":5.208437301},
{"learn":[0.01775556054],"iteration":259,"passed_time":5.619307431,"remaining_time":5.187053014},
{"learn":[0.01764799128],"iteration":260,"passed_time":5.640398153,"remaining_time":5.164962293},
{"learn":[0.0175509814],"iteration":261,"passed_time":5.66150424,"remaining_time":5.142893165},
{"learn":[0.01745742969],"iteration":262,"passed_time":5.686046687,"remaining_time":5.123928003},
{"learn":[0.01734655549],"iteration":263,"passed_time":5.707473568,"remaining_time":5.102135462},
{"learn":[0.01725968608],"iteration":264,"passed_time":5.728382877,"remaining_time":5.079886703},
{"learn":[0.01716637289],"iteration":265,"passed_time":5.749309121,"remaining_time":5.057662911},
{"learn":[0.0170686832],"iteration":266,"passed_time":5.772533457,"remaining_time":5.037454291},
{"learn":[0.01696531334],"iteration":267,"passed_time":5.793824107,"remaining_time":5.015549227},
{"learn":[0.01686381265],"iteration":268,"passed_time":5.814419458,"remaining_time":4.993051653},
{"learn":[0.01678307068],"iteration":269,"passed_time":5.835772294,"remaining_time":4.971213435},
{"learn":[0.0166944967],"iteration":270,"passed_time":5.858315646,"remaining_time":4.950384808},
{"learn":[0.01661269928],"iteration":271,"passed_time":5.882539699,"remaining_time":4.930952395},
{"learn":[0.01653543553],"iteration":272,"passed_time":5.903177012,"remaining_time":4.908502497},
{"learn":[0.01645896142],"iteration":273,"passed_time":5.922576399,"remaining_time":4.885044767},
{"learn":[0.01638291168],"iteration":274,"passed_time":5.941856058,"remaining_time":4.861518593},
{"learn":[0.01629983641],"iteration":275,"passed_time":5.960277593,"remaining_time":4.837326742},
{"learn":[0.01621638785],"iteration":276,"passed_time":5.982844282,"remaining_time":4.816513628},
{"learn":[0.01616559665],"iteration":277,"passed_time":6.001343168,"remaining_time":4.792439508},
{"learn":[0.01607382072],"iteration":278,"passed_time":6.021429141,"remaining_time":4.769662509},
{"learn":[0.01600293632],"iteration":279,"passed_time":6.041264202,"remaining_time":4.746707588},
{"learn":[0.01593812883],"iteration":280,"passed_time":6.063085053,"remaining_time":4.725322515},
{"learn":[0.01585654143],"iteration":281,"passed_time":6.086040308,"remaining_time":4.704811302},
{"learn":[0.01578147556],"iteration":282,"passed_time":6.106454291,"remaining_time":4.682334209},
{"learn":[0.01570414846],"iteration":283,"passed_time":6.126175162,"remaining_time":4.659344489},
{"learn":[0.0156271543],"iteration":284,"passed_time":6.14572412,"remaining_time":4.63624802},
{"learn":[0.01554959517],"iteration":285,"passed_time":6.168827349,"remaining_time":4.615835849},
{"learn":[0.01546658614],"iteration":286,"passed_time":6.188338404,"remaining_time":4.592738955},
{"learn":[0.01539902884],"iteration":287,"passed_time":6.207963314,"remaining_time":4.569750773},
{"learn":[0.01532499001],"iteration":288,"passed_time":6.226458794,"remaining_time":4.545961265},
{"learn":[0.0152589771],"iteration":289,"passed_time":6.245388747,"remaining_time":4.522522885},
{"learn":[0.01518339443],"iteration":290,"passed_time":6.268558407,"remaining_time":4.502160506},
{"learn":[0.01510234317],"iteration":291,"passed_time":6.28776204,"remaining_time":4.478953782},
{"learn":[0.01502759023],"iteration":292,"passed_time":6.305410293,"remaining_time":4.454675531},
{"learn":[0.01495782343],"iteration":293,"passed_time":6.323585604,"remaining_time":4.430811681},
{"learn":[0.01488791343],"iteration":294,"passed_time":6.341791404,"remaining_time":4.407007586},
{"learn":[0.01485084253],"iteration":295,"passed_time":6.362389498,"remaining_time":4.384890059},
{"learn":[0.01478414836],"iteration":296,"passed_time":6.380855766,"remaining_time":4.361325658},
{"learn":[0.01470311836],"iteration":297,"passed_time":6.398844423,"remaining_time":4.337471723},
{"learn":[0.01463642681],"iteration":298,"passed_time":6.436976374,"remaining_time":4.327198164},
{"learn":[0.01457693827],"iteration":299,"passed_time":6.459117626,"remaining_time":4.306078417},
{"learn":[0.01451569717],"iteration":300,"passed_time":6.474179142,"remaining_time":4.28027126},
{"learn":[0.0144565868],"iteration":301,"passed_time":6.492194647,"remaining_time":4.256471987},
{"learn":[0.01439564407],"iteration":302,"passed_time":6.50747786,"remaining_time":4.23093445},
{"learn":[0.01435886698],"iteration":303,"passed_time":6.523837034,"remaining_time":4.206158088},
{"learn":[0.01428907023],"iteration":304,"passed_time":6.541335883,"remaining_time":4.182165565},
{"learn":[0.01421866943],"iteration":305,"passed_time":6.558566533,"remaining_time":4.158045449},
{"learn":[0.01415447738],"iteration":306,"passed_time":6.576352779,"remaining_time":4.134319499},
{"learn":[0.01407277865],"iteration":307,"passed_time":6.603296049,"remaining_time":4.116340394},
{"learn":[0.01401427035],"iteration":308,"passed_time":6.631052851,"remaining_time":4.098806131},
{"learn":[0.01395247901],"iteration":309,"passed_time":6.657107471,"remaining_time":4.080162644},
{"learn":[0.01391438341],"iteration":310,"passed_time":6.681869496,"remaining_time":4.060685964},
{"learn":[0.01386740793],"iteration":311,"passed_time":6.706453868,"remaining_time":4.041068357},
{"learn":[0.01381770693],"iteration":312,"passed_time":6.739234928,"remaining_time":4.026316075},
{"learn":[0.01375788676],"iteration":313,"passed_time":6.765818912,"remaining_time":4.007778082},
{"learn":[0.0137042077],"iteration":314,"passed_time":6.791057519,"remaining_time":3.98839886},
{"learn":[0.01364159531],"iteration":315,"passed_time":6.824529258,"remaining_time":3.97377653},
{"learn":[0.01356935805],"iteration":316,"passed_time":6.848890559,"remaining_time":3.953775938},
{"learn":[0.01349839083],"iteration":317,"passed_time":6.878228252,"remaining_time":3.936596044},
{"learn":[0.01345851264],"iteration":318,"passed_time":6.900432638,"remaining_time":3.9152925},
{"learn":[0.01339256573],"iteration":319,"passed_time":6.915603288,"remaining_time":3.890026849},
{"learn":[0.01333788671],"iteration":320,"passed_time":6.946146061,"remaining_time":3.87339609},
{"learn":[0.01326752659],"iteration":321,"passed_time":6.970642628,"remaining_time":3.853336608},
{"learn":[0.01321308332],"iteration":322,"passed_time":6.991683335,"remaining_time":3.831355883},
{"learn":[0.01316381149],"iteration":323,"passed_time":7.010875609,"remaining_time":3.808376874},
{"learn":[0.01312827756],"iteration":324,"passed_time":7.039270501,"remaining_time":3.790376423},
{"learn":[0.01307514578],"iteration":325,"passed_time":7.069247711,"remaining_time":3.773156754},
{"learn":[0.01302406773],"iteration":326,"passed_time":7.09451547,"remaining_time":3.753367512},
{"learn":[0.01297178518],"iteration":327,"passed_time":7.123710496,"remaining_time":3.735604284},
{"learn":[0.0129220516],"iteration":328,"passed_time":7.14898288,"remaining_time":3.715732743},
{"learn":[0.01288844411],"iteration":329,"passed_time":7.17311548,"remaining_time":3.695241308},
{"learn":[0.01283555685],"iteration":330,"passed_time":7.207142313,"remaining_time":3.67977961},
{"learn":[0.01279335062],"iteration":331,"passed_time":7.229315466,"remaining_time":3.658207826},
{"learn":[0.01273285035],"iteration":332,"passed_time":7.256524556,"remaining_time":3.639157961},
{"learn":[0.01267557625],"iteration":333,"passed_time":7.291334318,"remaining_time":3.623836817},
{"learn":[0.01262901392],"iteration":334,"passed_time":7.324606743,"remaining_time":3.607642127},
{"learn":[0.01259864299],"iteration":335,"passed_time":7.35341382,"remaining_time":3.589166269},
{"learn":[0.0125669189],"iteration":336,"passed_time":7.382087521,"remaining_time":3.570564587},
{"learn":[0.01251198604],"iteration":337,"passed_time":7.411540817,"remaining_time":3.55227696},
{"learn":[0.01245918323],"iteration":338,"passed_time":7.439585601,"remaining_time":3.533254519},
{"learn":[0.01240115923],"iteration":339,"passed_time":7.467947343,"remaining_time":3.514328161},
{"learn":[0.01234739591],"iteration":340,"passed_time":7.500547179,"remaining_time":3.497322585},
{"learn":[0.01229628634],"iteration":341,"passed_time":7.529029175,"remaining_time":3.47832342},
{"learn":[0.01227921124],"iteration":342,"passed_time":7.558591764,"remaining_time":3.459763577},
{"learn":[0.01223087234],"iteration":343,"passed_time":7.595303227,"remaining_time":3.444381696},
{"learn":[0.01218410674],"iteration":344,"passed_time":7.619596183,"remaining_time":3.423296836},
{"learn":[0.01213335589],"iteration":345,"passed_time":7.647164399,"remaining_time":3.403651207},
{"learn":[0.01208498541],"iteration":346,"passed_time":7.681153993,"remaining_time":3.386791242},
{"learn":[0.012030353],"iteration":347,"passed_time":7.704837161,"remaining_time":3.365331174},
{"learn":[0.01198099576],"iteration":348,"passed_time":7.73307041,"remaining_time":3.345827026},
{"learn":[0.01193364679],"iteration":349,"passed_time":7.760175893,"remaining_time":3.325789668},
{"learn":[0.01188072421],"iteration":350,"passed_time":7.786361758,"remaining_time":3.305321658},
{"learn":[0.01183577801],"iteration":351,"passed_time":7.807182376,"remaining_time":3.282565317},
{"learn":[0.01178646869],"iteration":352,"passed_time":7.82388477,"remaining_time":3.258104989},
{"learn":[0.01174832784],"iteration":353,"passed_time":7.840179938,"remaining_time":3.233520539},
{"learn":[0.01170246663],"iteration":354,"passed_time":7.856309813,"remaining_time":3.208915276},
{"learn":[0.01165037197],"iteration":355,"passed_time":7.873553153,"remaining_time":3.184808017},
{"learn":[0.01160418015],"iteration":356,"passed_time":7.887625436,"remaining_time":3.159469012},
{"learn":[0.01155725],"iteration":357,"passed_time":7.901081582,"remaining_time":3.13394856},
{"learn":[0.01151484457],"iteration":358,"passed_time":7.914328968,"remaining_time":3.108413327},
{"learn":[0.01147289599],"iteration":359,"passed_time":7.928278638,"remaining_time":3.08321947},
{"learn":[0.01142558032],"iteration":360,"passed_time":7.945130257,"remaining_time":3.059205279},
{"learn":[0.01138274464],"iteration":361,"passed_time":7.957990257,"remaining_time":3.033708993},
{"learn":[0.01133445897],"iteration":362,"passed_time":7.967808024,"remaining_time":3.007134158},
{"learn":[0.01130125247],"iteration":363,"passed_time":7.975457426,"remaining_time":2.979841236},
{"learn":[0.01126130106],"iteration":364,"passed_time":7.982901756,"remaining_time":2.952580102},
{"learn":[0.01121935721],"iteration":365,"passed_time":7.992026826,"remaining_time":2.926042608},
{"learn":[0.01118211505],"iteration":366,"passed_time":7.999587717,"remaining_time":2.899033151},
{"learn":[0.01114442596],"iteration":367,"passed_time":8.007854722,"remaining_time":2.872382672},
{"learn":[0.01110333045],"iteration":368,"passed_time":8.015405964,"remaining_time":2.845577727},
{"learn":[0.01108282992],"iteration":369,"passed_time":8.023154958,"remaining_time":2.818946337},
{"learn":[0.01103754509],"iteration":370,"passed_time":8.03113516,"remaining_time":2.792497131},
{"learn":[0.01100222994],"iteration":371,"passed_time":8.040962439,"remaining_time":2.766782775},
{"learn":[0.01096118001],"iteration":372,"passed_time":8.048549774,"remaining_time":2.740390942},
{"learn":[0.01092319857],"iteration":373,"passed_time":8.056257004,"remaining_time":2.71414006},
{"learn":[0.01088056742],"iteration":374,"passed_time":8.063594038,"remaining_time":2.687864679},
{"learn":[0.0108323025],"iteration":375,"passed_time":8.071794979,"remaining_time":2.66197494},
{"learn":[0.01079443465],"iteration":376,"passed_time":8.079540845,"remaining_time":2.636030567},
{"learn":[0.01075893934],"iteration":377,"passed_time":8.089009714,"remaining_time":2.610738585},
{"learn":[0.01072404613],"iteration":378,"passed_time":8.098248239,"remaining_time":2.585456562},
{"learn":[0.01069685628],"iteration":379,"passed_time":8.10636868,"remaining_time":2.559905899},
{"learn":[0.01065662002],"iteration":380,"passed_time":8.113646155,"remaining_time":2.534183445},
{"learn":[0.01062053623],"iteration":381,"passed_time":8.122925542,"remaining_time":2.509175953},
{"learn":[0.01058570806],"iteration":382,"passed_time":8.133607355,"remaining_time":2.484679009},
{"learn":[0.0105550419],"iteration":383,"passed_time":8.143972099,"remaining_time":2.460158238},
{"learn":[0.01051978338],"iteration":384,"passed_time":8.153747092,"remaining_time":2.435534846},
{"learn":[0.01048168185],"iteration":385,"passed_time":8.161228124,"remaining_time":2.410310897},
{"learn":[0.01045894079],"iteration":386,"passed_time":8.16912625,"remaining_time":2.385300429},
{"learn":[0.01042578431],"iteration":387,"passed_time":8.176532696,"remaining_time":2.360236242},
{"learn":[0.01038964652],"iteration":388,"passed_time":8.184328972,"remaining_time":2.335374077},
{"learn":[0.01035795722],"iteration":389,"passed_time":8.19219264,"remaining_time":2.310618437},
{"learn":[0.01032542739],"iteration":390,"passed_time":8.200609421,"remaining_time":2.286103394},
{"learn":[0.01028553722],"iteration":391,"passed_time":8.208522324,"remaining_time":2.261531661},
{"learn":[0.01025123717],"iteration":392,"passed_time":8.216388816,"remaining_time":2.23703207},
{"learn":[0.01021198736],"iteration":393,"passed_time":8.223966086,"remaining_time":2.212539099},
{"learn":[0.01017351567],"iteration":394,"passed_time":8.234046927,"remaining_time":2.188797284},
{"learn":[0.01013904132],"iteration":395,"passed_time":8.241510032,"remaining_time":2.164436978},
{"learn":[0.01010716006],"iteration":396,"passed_time":8.249365648,"remaining_time":2.140263632},
{"learn":[0.01006779101],"iteration":397,"passed_time":8.258053896,"remaining_time":2.116385672},
{"learn":[0.01003498844],"iteration":398,"passed_time":8.265939127,"remaining_time":2.092380581},
{"learn":[0.01000985376],"iteration":399,"passed_time":8.273390718,"remaining_time":2.068347679},
{"learn":[0.0099774435],"iteration":400,"passed_time":8.28115624,"remaining_time":2.044474982},
{"learn":[0.009940079193],"iteration":401,"passed_time":8.289155129,"remaining_time":2.02073931},
{"learn":[0.009900836225],"iteration":402,"passed_time":8.296927501,"remaining_time":1.997027215},
{"learn":[0.009868085075],"iteration":403,"passed_time":8.304280568,"remaining_time":1.973294393},
{"learn":[0.009842715771],"iteration":404,"passed_time":8.312642175,"remaining_time":1.949879029},
{"learn":[0.009810791026],"iteration":405,"passed_time":8.320385322,"remaining_time":1.926394631},
{"learn":[0.009781394943],"iteration":406,"passed_time":8.332802167,"remaining_time":1.904055532},
{"learn":[0.00974747011],"iteration":407,"passed_time":8.34052515,"remaining_time":1.880706651},
{"learn":[0.009712501857],"iteration":408,"passed_time":8.349004311,"remaining_time":1.857602426},
{"learn":[0.009678129364],"iteration":409,"passed_time":8.35688639,"remaining_time":1.834438476},
{"learn":[0.009646033313],"iteration":410,"passed_time":8.364668258,"remaining_time":1.81132719},
{"learn":[0.009611241663],"iteration":411,"passed_time":8.372067178,"remaining_time":1.788208523},
{"learn":[0.009582808685],"iteration":412,"passed_time":8.38051413,"remaining_time":1.765386754},
{"learn":[0.009554692929],"iteration":413,"passed_time":8.387914037,"remaining_time":1.742416926},
{"learn":[0.009526177126],"iteration":414,"passed_time":8.3963206,"remaining_time":1.719728316},
{"learn":[0.009499903938],"iteration":415,"passed_time":8.403754459,"remaining_time":1.696911958},
{"learn":[0.009480884813],"iteration":416,"passed_time":8.411392731,"remaining_time":1.674210064},
{"learn":[0.009448536785],"iteration":417,"passed_time":8.420244345,"remaining_time":1.651818269},
{"learn":[0.00941728348],"iteration":418,"passed_time":8.429583423,"remaining_time":1.629585339},
{"learn":[0.009394512546],"iteration":419,"passed_time":8.438062648,"remaining_time":1.607250028},
{"learn":[0.009363522464],"iteration":420,"passed_time":8.450053193,"remaining_time":1.585639435},
{"learn":[0.009345922335],"iteration":421,"passed_time":8.457972587,"remaining_time":1.563321947},
{"learn":[0.009314595205],"iteration":422,"passed_time":8.465749385,"remaining_time":1.541046578},
{"learn":[0.00929006132],"iteration":423,"passed_time":8.47412764,"remaining_time":1.518947407},
{"learn":[0.009263545795],"iteration":424,"passed_time":8.481490099,"remaining_time":1.496733547},
{"learn":[0.009237188214],"iteration":425,"passed_time":8.489713943,"remaining_time":1.474739042},
{"learn":[0.009203985624],"iteration":426,"passed_time":8.499196406,"remaining_time":1.45302421},
{"learn":[0.009175478023],"iteration":427,"passed_time":8.507500938,"remaining_time":1.431168382},
{"learn":[0.009145544468],"iteration":428,"passed_time":8.522080921,"remaining_time":1.410414325},
{"learn":[0.009116135784],"iteration":429,"passed_time":8.530618508,"remaining_time":1.388705338},
{"learn":[0.00908671671],"iteration":430,"passed_time":8.538611792,"remaining_time":1.366970333},
{"learn":[0.009061829085],"iteration":431,"passed_time":8.545940119,"remaining_time":1.345194278},
{"learn":[0.009038545055],"iteration":432,"passed_time":8.554194795,"remaining_time":1.323628294},
{"learn":[0.009008292778],"iteration":433,"passed_time":8.561759946,"remaining_time":1.302018794},
{"learn":[0.008987033903],"iteration":434,"passed_time":8.569618717,"remaining_time":1.280517739},
{"learn":[0.008959085981],"iteration":435,"passed_time":8.579047662,"remaining_time":1.259309748},
{"learn":[0.008929838338],"iteration":436,"passed_time":8.586874881,"remaining_time":1.237924754},
{"learn":[0.008903779021],"iteration":437,"passed_time":8.594394593,"remaining_time":1.216558139},
{"learn":[0.008869303443],"iteration":438,"passed_time":8.603355978,"remaining_time":1.195454931},
{"learn":[0.008845444321],"iteration":439,"passed_time":8.611551975,"remaining_time":1.174302542},
{"learn":[0.008817061611],"iteration":440,"passed_time":8.621793415,"remaining_time":1.153482566},
{"learn":[0.008786831483],"iteration":441,"passed_time":8.631260652,"remaining_time":1.132608864},
{"learn":[0.008756599698],"iteration":442,"passed_time":8.641426823,"remaining_time":1.111876589},
{"learn":[0.008729996198],"iteration":443,"passed_time":8.651216237,"remaining_time":1.09114439},
{"learn":[0.008712174475],"iteration":444,"passed_time":8.658734351,"remaining_time":1.07018065},
{"learn":[0.008689851702],"iteration":445,"passed_time":8.666952887,"remaining_time":1.049362009},
{"learn":[0.008660236898],"iteration":446,"passed_time":8.674633184,"remaining_time":1.028535926},
{"learn":[0.008644124816],"iteration":447,"passed_time":8.683044657,"remaining_time":1.007853398},
{"learn":[0.00862352447],"iteration":448,"passed_time":8.69051047,"remaining_time":0.9871181157},
{"learn":[0.008597997086],"iteration":449,"passed_time":8.698129084,"remaining_time":0.9664587871},
{"learn":[0.008573817078],"iteration":450,"passed_time":8.706953527,"remaining_time":0.945988299},
{"learn":[0.00855764911],"iteration":451,"passed_time":8.719932874,"remaining_time":0.9260105707},
{"learn":[0.008544663397],"iteration":452,"passed_time":8.729813837,"remaining_time":0.9057422745},
{"learn":[0.008524962308],"iteration":453,"passed_time":8.739588052,"remaining_time":0.8855089216},
{"learn":[0.008495200532],"iteration":454,"passed_time":8.750190225,"remaining_time":0.8654034288},
{"learn":[0.008467355042],"iteration":455,"passed_time":8.758685691,"remaining_time":0.8451363386},
{"learn":[0.008442139251],"iteration":456,"passed_time":8.76714435,"remaining_time":0.8249173021},
{"learn":[0.008411263009],"iteration":457,"passed_time":8.774669289,"remaining_time":0.804663996},
{"learn":[0.00838761627],"iteration":458,"passed_time":8.782912192,"remaining_time":0.7845302829},
{"learn":[0.008359662301],"iteration":459,"passed_time":8.790835367,"remaining_time":0.7644204667},
{"learn":[0.008334856353],"iteration":460,"passed_time":8.799965374,"remaining_time":0.7444656173},
{"learn":[0.008312491603],"iteration":461,"passed_time":8.808513234,"remaining_time":0.7245097465},
{"learn":[0.008290158278],"iteration":462,"passed_time":8.820356356,"remaining_time":0.7048664907},
{"learn":[0.008264234139],"iteration":463,"passed_time":8.828517575,"remaining_time":0.6849711912},
{"learn":[0.008239029538],"iteration":464,"passed_time":8.836657616,"remaining_time":0.6651247668},
{"learn":[0.008220801966],"iteration":465,"passed_time":8.844563797,"remaining_time":0.6453115217},
{"learn":[0.008194687154],"iteration":466,"passed_time":8.854398244,"remaining_time":0.625685529},
{"learn":[0.008169304822],"iteration":467,"passed_time":8.864087623,"remaining_time":0.6060914614},
{"learn":[0.008146099487],"iteration":468,"passed_time":8.871410796,"remaining_time":0.5863832296},
{"learn":[0.008122980048],"iteration":469,"passed_time":8.879751415,"remaining_time":0.5667926435},
{"learn":[0.008101160417],"iteration":470,"passed_time":8.887761772,"remaining_time":0.5472294934},
{"learn":[0.008076245183],"iteration":471,"passed_time":8.895903833,"remaining_time":0.5277231087},
{"learn":[0.008052476443],"iteration":472,"passed_time":8.903942003,"remaining_time":0.5082588458},
{"learn":[0.008031260906],"iteration":473,"passed_time":8.912961421,"remaining_time":0.488896618},
{"learn":[0.008008785555],"iteration":474,"passed_time":8.922071002,"remaining_time":0.4695826843},
{"learn":[0.007987683891],"iteration":475,"passed_time":8.931533362,"remaining_time":0.4503294132},
{"learn":[0.007962988875],"iteration":476,"passed_time":8.938899608,"remaining_time":0.4310161236},
{"learn":[0.007941438038],"iteration":477,"passed_time":8.94723402,"remaining_time":0.4117973817},
{"learn":[0.007922056712],"iteration":478,"passed_time":8.954707046,"remaining_time":0.3925863214},
{"learn":[0.00789765702],"iteration":479,"passed_time":8.965188441,"remaining_time":0.3735495184},
{"learn":[0.007876623556],"iteration":480,"passed_time":8.973610527,"remaining_time":0.3544669439},
{"learn":[0.007863574435],"iteration":481,"passed_time":8.982127968,"remaining_time":0.3354321648},
{"learn":[0.007850622121],"iteration":482,"passed_time":8.990297869,"remaining_time":0.3164287035},
{"learn":[0.007826026687],"iteration":483,"passed_time":8.998244076,"remaining_time":0.2974626141},
{"learn":[0.007806296859],"iteration":484,"passed_time":9.006856494,"remaining_time":0.278562572},
{"learn":[0.0077910334],"iteration":485,"passed_time":9.019619218,"remaining_time":0.2598244219},
{"learn":[0.007770742062],"iteration":486,"passed_time":9.027459866,"remaining_time":0.2409794215},
{"learn":[0.007750900483],"iteration":487,"passed_time":9.034792782,"remaining_time":0.2221670356},
{"learn":[0.007733012326],"iteration":488,"passed_time":9.042585761,"remaining_time":0.2034119496},
{"learn":[0.007713422604],"iteration":489,"passed_time":9.050517754,"remaining_time":0.184704444},
{"learn":[0.007693088327],"iteration":490,"passed_time":9.059536254,"remaining_time":0.166060746},
{"learn":[0.00767093694],"iteration":491,"passed_time":9.066924079,"remaining_time":0.1474296598},
{"learn":[0.007649780669],"iteration":492,"passed_time":9.074854433,"remaining_time":0.1288518885},
{"learn":[0.00762654612],"iteration":493,"passed_time":9.082235774,"remaining_time":0.110310556},
{"learn":[0.007601483387],"iteration":494,"passed_time":9.089809147,"remaining_time":0.09181625401},
{"learn":[0.007580537256],"iteration":495,"passed_time":9.098264104,"remaining_time":0.07337309761},
{"learn":[0.007557051607],"iteration":496,"passed_time":9.111200143,"remaining_time":0.05499718396},
{"learn":[0.00753865815],"iteration":497,"passed_time":9.118864383,"remaining_time":0.03662194531},
{"learn":[0.007515641412],"iteration":498,"passed_time":9.128467147,"remaining_time":0.01829352134},
{"learn":[0.007506055061],"iteration":499,"passed_time":9.136344254,"remaining_time":0}
]}2101749},
{"learn":[0.00598835832],"iteration":499,"passed_time":11.0524576,"remaining_time":0}
]}